{
  "metadata": {
    "timestamp": "2025-04-21T15:46:22.057007",
    "platform": "macOS-15.4.1-arm64-arm-64bit-Mach-O",
    "machine_type": "arm64",
    "processor": "arm",
    "cpu_count_logical": 12,
    "cpu_count_physical": 12,
    "total_memory_mb": 24576.0,
    "python_version": "3.13.2",
    "test_framework_version": "stdlib (3.13.2)"
  },
  "framework": "unittest",
  "test_suite": "fibonacci",
  "runs": [
    {
      "iteration": 1,
      "execution_time_seconds": 0.04025602340698242,
      "min_memory_mb": 0.15625,
      "peak_memory_mb": 15.0,
      "cpu_user_time_seconds": 0.018826456999999998,
      "cpu_system_time_seconds": 0.0057764159999999995,
      "thread_count": 1,
      "exit_code": 0
    },
    {
      "iteration": 2,
      "execution_time_seconds": 0.04199671745300293,
      "min_memory_mb": 0.625,
      "peak_memory_mb": 12.609375,
      "cpu_user_time_seconds": 0.017792208,
      "cpu_system_time_seconds": 0.006244,
      "thread_count": 1,
      "exit_code": 0
    },
    {
      "iteration": 3,
      "execution_time_seconds": 0.054662227630615234,
      "min_memory_mb": 0.15625,
      "peak_memory_mb": 15.53125,
      "cpu_user_time_seconds": 0.027785458,
      "cpu_system_time_seconds": 0.00737175,
      "thread_count": 1,
      "exit_code": 0
    },
    {
      "iteration": 4,
      "execution_time_seconds": 0.04423022270202637,
      "min_memory_mb": 0.15625,
      "peak_memory_mb": 13.125,
      "cpu_user_time_seconds": 0.018832499000000003,
      "cpu_system_time_seconds": 0.0057005,
      "thread_count": 1,
      "exit_code": 0
    },
    {
      "iteration": 5,
      "execution_time_seconds": 0.04388785362243652,
      "min_memory_mb": 0.15625,
      "peak_memory_mb": 12.84375,
      "cpu_user_time_seconds": 0.018323082,
      "cpu_system_time_seconds": 0.006172958000000001,
      "thread_count": 1,
      "exit_code": 0
    },
    {
      "iteration": 6,
      "execution_time_seconds": 0.049833059310913086,
      "min_memory_mb": 0.15625,
      "peak_memory_mb": 15.171875,
      "cpu_user_time_seconds": 0.02557775,
      "cpu_system_time_seconds": 0.007053499999999999,
      "thread_count": 1,
      "exit_code": 0
    },
    {
      "iteration": 7,
      "execution_time_seconds": 0.042450904846191406,
      "min_memory_mb": 0.15625,
      "peak_memory_mb": 13.0625,
      "cpu_user_time_seconds": 0.018582334,
      "cpu_system_time_seconds": 0.0059212909999999995,
      "thread_count": 1,
      "exit_code": 0
    },
    {
      "iteration": 8,
      "execution_time_seconds": 0.04391908645629883,
      "min_memory_mb": 0.15625,
      "peak_memory_mb": 13.0,
      "cpu_user_time_seconds": 0.018487875,
      "cpu_system_time_seconds": 0.006045375,
      "thread_count": 1,
      "exit_code": 0
    },
    {
      "iteration": 9,
      "execution_time_seconds": 0.04372382164001465,
      "min_memory_mb": 0.15625,
      "peak_memory_mb": 13.046875,
      "cpu_user_time_seconds": 0.018792833999999998,
      "cpu_system_time_seconds": 0.0056725,
      "thread_count": 1,
      "exit_code": 0
    },
    {
      "iteration": 10,
      "execution_time_seconds": 0.04402899742126465,
      "min_memory_mb": 0.171875,
      "peak_memory_mb": 12.4375,
      "cpu_user_time_seconds": 0.028984,
      "cpu_system_time_seconds": 0.007291291,
      "thread_count": 1,
      "exit_code": 0
    }
  ]
}